{
   "CodeGenerationMode": 0,
   "ContextClassName": "ParkeringsdatadbContext",
   "ContextNamespace": "Models",
   "DefaultDacpacSchema": null,
   "FilterSchemas": false,
   "IncludeConnectionString": true,
   "ModelNamespace": null,
   "OutputContextPath": "Models",
   "OutputPath": "Models",
   "ProjectRootNamespace": "ParkeringsDataAPI",
   "Schemas": null,
   "SelectedHandlebarsLanguage": 0,
   "SelectedToBeGenerated": 0,
   "Tables": [
      {
         "Name": "[dbo].[Log]",
         "ObjectType": 0
      },
      {
         "Name": "[dbo].[Parkeringsområde]",
         "ObjectType": 0
      },
      {
         "Name": "[dbo].[SpecielleParkeringsPladser]",
         "ObjectType": 0
      }
   ],
   "UiHint": "emilzealanddb.ParkeringsDataDb",
   "UseBoolPropertiesWithoutDefaultSql": false,
   "UseDatabaseNames": false,
   "UseDbContextSplitting": false,
   "UseFluentApiOnly": false,
   "UseHandleBars": false,
   "UseInflector": true,
   "UseLegacyPluralizer": false,
   "UseNoConstructor": false,
   "UseNoDefaultConstructor": false,
   "UseNoNavigations": false,
   "UseNoObjectFilter": false,
   "UseNodaTime": false,
   "UseNullableReferences": false,
   "UseSchemaFolders": false,
   "UseSpatial": false
}